BinaryTK_CardboardDog/Character.py
BinaryTK_CardboardDog/Integer.py
BinaryTK_CardboardDog/__init__.py
BinaryTK_CardboardDog-0.0.1.dist-info/LICENSE
BinaryTK_CardboardDog-0.0.1.dist-info/METADATA
BinaryTK_CardboardDog-0.0.1.dist-info/WHEEL
BinaryTK_CardboardDog-0.0.1.dist-info/top_level.txt
BinaryTK_CardboardDog-0.0.1.dist-info/RECORD
